LICENSE
MANIFEST.in
NOTES
build.py
setup.py
bin/zapps
examples/calc.g
examples/calc.py
examples/command.g
examples/command.py
examples/expr.g
examples/expr.py
examples/lisp.g
examples/lisp.py
examples/make.g
examples/stackish.g
examples/stackish.py
examples/test.g
examples/test.py
manual/Makefile
manual/img1.png
manual/yapps2.tex
zapps/__init__.py
zapps/parser.py
zapps/rt.py
zapps/support.py
zapps.egg-info/PKG-INFO
zapps.egg-info/SOURCES.txt
zapps.egg-info/dependency_links.txt
zapps.egg-info/top_level.txt
