Metadata-Version: 1.0
Name: zapps
Version: 0.5
Summary: A book compiler for programmers where code and prose are separate.
Home-page: http://www.zedshaw.com/projects/zapps
Author: Zed A. Shaw
Author-email: zedshaw@zedshaw.com
License: UNKNOWN
Platform: UNKNOWN
